differt_core-0.6.2.dist-info/METADATA
differt_core-0.6.2.dist-info/WHEEL
differt_core-0.6.2.dist-info/licenses/LICENSE.md
differt_core/__init__.py
differt_core/_differt_core.cpython-314t-arm-linux-gnueabihf.so
differt_core/_differt_core/__init__.pyi
differt_core/_differt_core/geometry/triangle_mesh.pyi
differt_core/_differt_core/rt/__init__.pyi
differt_core/_differt_core/rt/graph.pyi
differt_core/_differt_core/scene/sionna.pyi
differt_core/_differt_core/scene/triangle_scene.pyi
differt_core/geometry/__init__.py
differt_core/geometry/_triangle_mesh.py
differt_core/py.typed
differt_core/rt/__init__.py
differt_core/rt/_graph.py
differt_core/scene/__init__.py
differt_core/scene/_sionna.py
differt_core/scene/_triangle_scene.py
differt_core-0.6.2.dist-info/RECORD
