Metadata-Version: 2.4
Name: differt-core
Version: 0.6.2
Classifier: Programming Language :: Python :: 3
Classifier: Programming Language :: Python :: 3.11
Classifier: Programming Language :: Python :: 3.12
Classifier: Programming Language :: Python :: 3.13
Classifier: Programming Language :: Python :: 3.14
Classifier: Programming Language :: Python :: Free Threading
Classifier: Operating System :: OS Independent
Classifier: Topic :: Scientific/Engineering
Classifier: Programming Language :: Rust
Classifier: Programming Language :: Python :: Implementation :: CPython
Classifier: Programming Language :: Python :: Implementation :: PyPy
Requires-Dist: numpy>=1.20
License-File: LICENSE.md
Summary: Core backend of DiffeRT implemented in Rust
Keywords: ray tracing,differentiable,propagation,radio,jax
Author-email: Jérome Eertmans <jeertmans@icloud.com>
Requires-Python: >=3.11
